pynetcf/__init__.py
pynetcf/base.py
pynetcf/image.py
pynetcf/point_data.py
pynetcf/time_series.py
pynetcf-0.5.1.dist-info/LICENSE.txt
pynetcf-0.5.1.dist-info/METADATA
pynetcf-0.5.1.dist-info/WHEEL
pynetcf-0.5.1.dist-info/top_level.txt
pynetcf-0.5.1.dist-info/RECORD
