Metadata-Version: 2.1
Name: pynetcf
Version: 0.5.1
Summary: Reading and writing netCDF files according to CF conventions
Home-page: http://geo.tuwien.ac.at/
Author: TU Wien
Author-email: remote.sensing@geo.tuwien.ac.at
License: MIT
Project-URL: Documentation, http://pynetcf.readthedocs.org/
Platform: any
Classifier: Development Status :: 4 - Beta
Classifier: Programming Language :: Python
Requires-Python: >=3.8
License-File: LICENSE.txt
Requires-Dist: importlib-metadata
Requires-Dist: numpy
Requires-Dist: pandas
Requires-Dist: netCDF4
Requires-Dist: pygeogrids
Requires-Dist: pygeobase
Provides-Extra: testing
Requires-Dist: pytest; extra == "testing"
Requires-Dist: pytest-cov; extra == "testing"
